lutzpocflux/__init__.py
lutzpocflux/__main__.py
lutzpocflux/equations.py
lutzpocflux/lutzpocflux.py
lutzpocflux-0.1.5.dist-info/METADATA
lutzpocflux-0.1.5.dist-info/WHEEL
lutzpocflux-0.1.5.dist-info/RECORD
