Metadata-Version: 2.1
Name: lutzpocflux
Version: 0.1.5
Summary: Calculate POC Export flux, as Lutz et al. 2007
Author: Alex Webber
Author-email: alexpwebber@gmail.com
Requires-Python: >=3.10,<4.0
Classifier: License :: OSI Approved :: MIT License
Classifier: Operating System :: OS Independent
Classifier: Programming Language :: Python :: 3
Classifier: Programming Language :: Python :: 3.10
Classifier: Programming Language :: Python :: 3.11
Classifier: Programming Language :: Python :: 3.12
Requires-Dist: numpy (==1.26.4)
Project-URL: Homepage, https://github.com/apwebber/LutzPOCFlux
Project-URL: Issues, https://github.com/apwebber/LutzPOCFlux/issues
